glyphtools/__init__.py
glyphtools/babelfont.py
glyphtools/ckmeans.py
glyphtools/glyphs.py
glyphtools-0.8.0.dist-info/AUTHORS.rst
glyphtools-0.8.0.dist-info/LICENSE
glyphtools-0.8.0.dist-info/METADATA
glyphtools-0.8.0.dist-info/WHEEL
glyphtools-0.8.0.dist-info/top_level.txt
glyphtools-0.8.0.dist-info/RECORD
