Metadata-Version: 2.1
Name: glyphtools
Version: 0.8.0
Summary: Routines for extracting information from fontTools glyphs
Home-page: https://github.com/simoncozens/glyphtools
Author: Simon Cozens
Author-email: simon@simon-cozens.org
License: Apache Software License 2.0
Keywords: glyphtools
Platform: UNKNOWN
Classifier: Development Status :: 2 - Pre-Alpha
Classifier: Intended Audience :: Developers
Classifier: License :: OSI Approved :: Apache Software License
Classifier: Natural Language :: English
Classifier: Programming Language :: Python :: 3
Classifier: Programming Language :: Python :: 3.5
Classifier: Programming Language :: Python :: 3.6
Classifier: Programming Language :: Python :: 3.7
Classifier: Programming Language :: Python :: 3.8
Requires-Python: >=3.5
License-File: LICENSE
License-File: AUTHORS.rst
